CHANGES.txt
LICENSE.txt
MANIFEST.in
README.txt
setup.py
js/__init__.py
js.angular_ui_sortable.egg-info/PKG-INFO
js.angular_ui_sortable.egg-info/SOURCES.txt
js.angular_ui_sortable.egg-info/dependency_links.txt
js.angular_ui_sortable.egg-info/entry_points.txt
js.angular_ui_sortable.egg-info/namespace_packages.txt
js.angular_ui_sortable.egg-info/not-zip-safe
js.angular_ui_sortable.egg-info/requires.txt
js.angular_ui_sortable.egg-info/top_level.txt
js/angular_ui_sortable/__init__.py
js/angular_ui_sortable/test_angular_ui_sortable.txt
js/angular_ui_sortable/resources/sortable.js
js/angular_ui_sortable/resources/sortable.min.js