Metadata-Version: 1.0
Name: js.angular-ui-sortable
Version: 0.13.4
Summary: Fanstatic packaging of Angular UI Sortable
Home-page: UNKNOWN
Author: Fanstatic Developers
Author-email: fanstatic@googlegroups.com
License: BSD
Platform: UNKNOWN
